muse_sc/__init__.py
muse_sc/muse_architecture.py
muse_sc/triplet_loss.py
muse_sc-0.0.8.dist-info/LICENSE
muse_sc-0.0.8.dist-info/METADATA
muse_sc-0.0.8.dist-info/WHEEL
muse_sc-0.0.8.dist-info/top_level.txt
muse_sc-0.0.8.dist-info/RECORD
