Metadata-Version: 2.1
Name: muse-sc
Version: 0.0.8
Summary: MUSE is a deep learning approach characterizing tissue composition through combined analysis of morphologies and transcriptional states for single-cell spatial transcriptomics data.
Home-page: https://github.com/AltschulerWu-Lab/MUSE
Author: Feng Bao @ AltschulerWu-Lab
Author-email: feng.bao@ucsf.edu
License: MIT
Keywords: single-cell analysis,deep learning,spatial transcriptomics
Platform: UNKNOWN
